HISTORY.rst
LICENSE
MANIFEST.in
README.rst
requirements.txt
setup.py
incursion/__init__.py
incursion/continuous_queries.py
incursion/query.py
incursion.egg-info/PKG-INFO
incursion.egg-info/SOURCES.txt
incursion.egg-info/dependency_links.txt
incursion.egg-info/not-zip-safe
incursion.egg-info/requires.txt
incursion.egg-info/top_level.txt