Metadata-Version: 1.1
Name: incursion
Version: 0.4.0
Summary: Python InfluxDB Client for Developers.
Home-page: http://github.com/voidfiles/incursion
Author: Alex Kessinger
Author-email: voidfiles@gmail.com
License: MIT
Platform: UNKNOWN
Classifier: Development Status :: 4 - Beta
Classifier: Intended Audience :: Developers
Classifier: Natural Language :: English
Classifier: License :: OSI Approved :: MIT License
Classifier: Programming Language :: Python
